odoo/addons/fieldservice_vehicle/README.rst
odoo/addons/fieldservice_vehicle/__init__.py
odoo/addons/fieldservice_vehicle/__manifest__.py
odoo/addons/fieldservice_vehicle/i18n/de.po
odoo/addons/fieldservice_vehicle/i18n/es.po
odoo/addons/fieldservice_vehicle/i18n/es_AR.po
odoo/addons/fieldservice_vehicle/i18n/es_CL.po
odoo/addons/fieldservice_vehicle/i18n/fieldservice_vehicle.pot
odoo/addons/fieldservice_vehicle/i18n/it.po
odoo/addons/fieldservice_vehicle/i18n/pt_BR.po
odoo/addons/fieldservice_vehicle/models/__init__.py
odoo/addons/fieldservice_vehicle/models/fsm_order.py
odoo/addons/fieldservice_vehicle/models/fsm_person.py
odoo/addons/fieldservice_vehicle/models/fsm_vehicle.py
odoo/addons/fieldservice_vehicle/readme/CONFIGURE.md
odoo/addons/fieldservice_vehicle/readme/CONTRIBUTORS.md
odoo/addons/fieldservice_vehicle/readme/CREDITS.md
odoo/addons/fieldservice_vehicle/readme/DESCRIPTION.md
odoo/addons/fieldservice_vehicle/readme/INSTALL.md
odoo/addons/fieldservice_vehicle/readme/ROADMAP.md
odoo/addons/fieldservice_vehicle/readme/USAGE.md
odoo/addons/fieldservice_vehicle/security/ir.model.access.csv
odoo/addons/fieldservice_vehicle/security/res_groups.xml
odoo/addons/fieldservice_vehicle/static/description/icon.png
odoo/addons/fieldservice_vehicle/static/description/index.html
odoo/addons/fieldservice_vehicle/tests/__init__.py
odoo/addons/fieldservice_vehicle/tests/test_fsm_vehicle.py
odoo/addons/fieldservice_vehicle/views/fsm_order.xml
odoo/addons/fieldservice_vehicle/views/fsm_person.xml
odoo/addons/fieldservice_vehicle/views/fsm_vehicle.xml
odoo/addons/fieldservice_vehicle/views/menu.xml
odoo_addon_fieldservice_vehicle-18.0.1.0.0.2.dist-info/METADATA
odoo_addon_fieldservice_vehicle-18.0.1.0.0.2.dist-info/WHEEL
odoo_addon_fieldservice_vehicle-18.0.1.0.0.2.dist-info/top_level.txt
odoo_addon_fieldservice_vehicle-18.0.1.0.0.2.dist-info/RECORD
